<?xml version="1.0" encoding="utf-8"?>
<!DOCTYPE hibernate-mapping PUBLIC "-//Hibernate/Hibernate Mapping DTD 3.0//EN"
"http://hibernate.sourceforge.net/hibernate-mapping-3.0.dtd">
<!-- 
    Mapping file autogenerated by MyEclipse Persistence Tools
-->
<hibernate-mapping>
    <class name="com.cubepro.staff.StaffDetails" table="staff_details" dynamic-insert="true" dynamic-update="true">
        <id name="staffId" type="java.lang.Integer">
            <column name="staff_id" />
            <generator class="assigned" />
        </id>
        <!--  <many-to-one name="classDetails" class="com.cubepro.classes.ClassDetails" fetch="select">
            <column name="class_id" not-null="true" />
        </many-to-one>-->
        <property name="firstName" type="java.lang.String">
            <column name="first_name" length="45"  />
        </property>
        <property name="staffNo" type="java.lang.String" formula="(SELECT concat('STAFF','-00',s.staff_id) FROM staff_details s where s.staff_id = staff_id)">
            <column name="staff_no" length="45"  />
        </property>
        <property name="dobString" type="java.lang.String">
            <column name="dob" length="19"  />
        </property>
        <property name="dojString" type="java.lang.String">
            <column name="doj" length="19"  />
        </property>
        <property name="fatherName" type="java.lang.String">
            <column name="father_name" length="45"  />
        </property>
        <property name="motherName" type="java.lang.String">
            <column name="mother_name" length="45" />
        </property>
        <property name="guardianName" type="java.lang.String">
            <column name="guardian_name" length="45" />
        </property>
        <property name="address1" type="java.lang.String">
            <column name="address_1" length="45"  />
        </property>
        <property name="address2" type="java.lang.String">
            <column name="address_2" length="45" />
        </property>
        <property name="city" type="java.lang.String">
            <column name="city" length="45"  />
        </property>
        <property name="state" type="java.lang.String">
            <column name="state" length="45"  />
        </property>
        <property name="country" type="java.lang.String">
            <column name="country" length="45"  />
        </property>
        <property name="zipCode" type="java.lang.String">
            <column name="zipCode" length="45"  />
        </property>
        <property name="phone" type="java.lang.String">
            <column name="phone" length="45" />
        </property>
        <property name="mobile" type="java.lang.String">
            <column name="mobile" length="45" />
        </property>
        <property name="salaryAmount" type="java.lang.Double">
            <column name="salary_amount" precision="22" scale="0"  />
        </property>
        <property name="sex" type="java.lang.String">
            <column name="sex" length="1"  />
        </property>
        <property name="qualification" type="java.lang.String">
            <column name="qualification" length="100"  />
        </property>
        <property name="designation" type="java.lang.String">
            <column name="designation" length="50"  />
        </property>
        <property name="subjectHandled1" type="java.lang.String">
            <column name="subject_handled_1" length="30"  />
        </property>
        <property name="subjectHandled2" type="java.lang.String">
            <column name="subject_handled_2" length="30"  />
        </property>
        <property name="subjectHandled3" type="java.lang.String">
            <column name="subject_handled_3" length="30"  />
        </property>
        <property name="subjectHandled4" type="java.lang.String">
            <column name="subject_handled_4" length="30"  />
        </property>
        <property name="createDate" type="java.util.Date">
            <column name="create_date" length="19"  />
        </property>
        <property name="createUserId" type="java.lang.Integer">
            <column name="create_user_id"  />
        </property>
        <property name="changeDate" type="java.util.Date">
            <column name="change_date" length="19" />
        </property>
        <property name="changeUserId" type="java.lang.Integer">
            <column name="change_user_id" />
        </property>
        <property name="statusId" type="java.lang.Integer">
            <column name="status_id"  />
        </property>
        <property name="secondName" type="java.lang.String">
            <column name="second_name" length="45"  />
        </property>
        <property name="dept" type="java.lang.String">
            <column name="dept" length="45"  />
        </property>
        <property name="prevEmp" type="java.lang.String">
            <column name="prev_emp_det" length="45"  />
        </property>
        <property name="houseNo" type="java.lang.String">
            <column name="house_no" length="45"  />
        </property>
        <property name="houseName" type="java.lang.String">
            <column name="house_name" length="45"  />
        </property>
        <property name="street" type="java.lang.String">
            <column name="street" length="45"  />
        </property>
        <property name="pin" type="java.lang.String">
            <column name="pin" length="45"  />
        </property>
                <property name="district" type="java.lang.String">
            <column name="dist" length="45"  />
        </property>
        <property name="email" type="java.lang.String">
            <column name="email" length="45"  />
        </property>
        <property name="basicPay" type="java.lang.String">
            <column name="basic_pay" length="45"  />
        </property>
        <property name="hra" type="java.lang.String">
            <column name="hra" length="45"  />
        </property>
        <property name="da" type="java.lang.String">
            <column name="da" length="45"  />
        </property>
        <property name="allow1" type="java.lang.String">
            <column name="allow1" length="45"  />
        </property>
        <property name="allow2" type="java.lang.String">
            <column name="allow2" length="45"  />
        </property>
        <property name="pfAmt" type="java.lang.String">
            <column name="pf_amt" length="45"  />
        </property>
        <property name="others" type="java.lang.String">
            <column name="others" length="45"  />
        </property>
        <property name="pfAcc" type="java.lang.String">
            <column name="pf_acc" length="45"  />
        </property>
        <property name="loanAmt" type="java.lang.String">
            <column name="loan_amt" length="45"  />
        </property>
        <property name="esiAmt" type="java.lang.String">
            <column name="esi_amt" length="45"  />
        </property>
        <property name="esiAcc" type="java.lang.String">
            <column name="esi_acc" length="45"  />
        </property>
        <property name="esiOthers" type="java.lang.String">
            <column name="esi_others" length="45"  />
        </property>
        <property name="d_p" type="java.lang.String">
            <column name="d_p" length="45"  />
        </property>    
        <property name="p_p" type="java.lang.String">
            <column name="p_p" length="45"  />
        </property>
        <property name="m_a" type="java.lang.String">
            <column name="m_a" length="45"  />
        </property>
        <property name="o_a" type="java.lang.String">
            <column name="o_a" length="45"  />
        </property> 
        <property name="sa" type="java.lang.String">
            <column name="sa" length="45"  />
        </property>
        <property name="fbf" type="java.lang.String">
            <column name="fbf" length="45"  />
        </property>
        <property name="hf" type="java.lang.String">
            <column name="hf" length="45"  />
        </property> 
        <property name="pf_cont" type="java.lang.String">
            <column name="pf_cont" length="45"  />
        </property> 
        <property name="pf_rec" type="java.lang.String">
            <column name="pf_rec" length="45"  />
        </property> 
        <property name="fa" type="java.lang.String">
            <column name="fa" length="45"  />
        </property>  
        <property name="spf_1" type="java.lang.String">
            <column name="spf_1" length="45"  />
        </property> 
        <property name="ntc" type="java.lang.String">
            <column name="ntc" length="45"  />
        </property> 
        <property name="t_a" type="java.lang.String">
            <column name="t_a" length="45"  />
        </property> 
        <property name="cma" type="java.lang.String">
            <column name="cma" length="45"  />
        </property> 
        <property name="diocesan" type="java.lang.String">
            <column name="diocesan" length="45"  />
        </property>
        <property name="lic" type="java.lang.String">
            <column name="lic" length="45"  />
        </property>  
        <property name="rd" type="java.lang.String">
            <column name="rd" length="45"  />
        </property>  
        <property name="pli" type="java.lang.String">
            <column name="pli" length="45"  />
        </property>
        <property name="guild" type="java.lang.String">
            <column name="guild" length="45"  />
        </property>  
        <property name="staff_ex" type="java.lang.String">
            <column name="staff_ex" length="45"  />
        </property>  
        <property name="p_tax" type="java.lang.String">
            <column name="p_tax" length="45"  />
        </property>  
        <property name="co_optex" type="java.lang.String">
            <column name="co_optex" length="45"  />
        </property> 
        <property name="misc" type="java.lang.String">
            <column name="misc" length="45"  />
        </property> 
        <property name="stamp" type="java.lang.String">
            <column name="stamp" length="45"  />
        </property>                                                                                                                                                                                              
        <property name="tdsAmt" type="java.lang.String">
            <column name="tds_amt" length="45"  />
        </property>
        <property name="tdsAcc" type="java.lang.String">
            <column name="tds_acc" length="45"  />
        </property>
        <property name="bankName" type="java.lang.String">
            <column name="bank_name" length="45"  />
        </property>
        <property name="bankAcc" type="java.lang.String">
            <column name="bank_acc" length="45"  />
        </property>
        <property name="type" type="java.lang.String">
            <column name="type" length="45"  />
        </property>
        <property name="isUsingTransport" type="java.lang.String">
            <column name="is_using_transport" length="45" />
        </property>
        <property name="isUsingHostel" type="java.lang.String">
            <column name="is_using_hostel" length="45" />
        </property>
        <property name="isUsingLibrary" type="java.lang.String">
            <column name="is_using_library" length="45" />
        </property>
        <property name="isUsingLab" type="java.lang.String">
            <column name="is_using_lab" length="45" />
        </property>
        <property name="photo" type="java.lang.String">
            <column name="photo" length="145" />
        </property>
        <property name="routeStopId" type="java.lang.Integer">
            <column name="route_stop_id" />
        </property>
        <property name="roomId" type="java.lang.Integer">
            <column name="room_id" />
        </property>        
        <set name="timeTableDetailsesForReplacementStaffId" inverse="true">
            <key>
                <column name="replacement_staff_id"  />
            </key>
            <one-to-many class="com.cubepro.timetable.TimeTableDetails" />
        </set>
        <set name="timeTableDetailsesForStaffId" inverse="true">
            <key>
                <column name="staff_id"  />
            </key>
            <one-to-many class="com.cubepro.timetable.TimeTableDetails" />
        </set>
    </class>
</hibernate-mapping>
